Workbook
Name NativeTimeline_Order_Date: #N/A
Name Slicer_Category: #N/A
Name Slicer_Payment_Mode: #N/A
Name Slicer_Region: #N/A
Name Slicer_Salesperson: #N/A

Sheet Salesperson
A3: Row Labels | B3: Sum of Net Sales
A4: Devi | B4: 1046263
A5: Bheema | B5: 1019045.6
A6: Anil | B6: 780218.4
A7: Kiran | B7: 637487
A8: Srinu | B8: 599020
A9: Sneha | B9: 430876.5
A10: Pavani | B10: 233519
A11: Ravi | B11: 169960.6
A12: Grand Total | B12: 4916390.1

Sheet Netsales
A3: Row Labels | B3: Sum of Net Sales
A4: East | B4: 768980.6
A5: North | B5: 1799264
A6: South | B6: 1477139.5
A7: West | B7: 871006
A8: Grand Total | B8: 4916390.1

Sheet Category
A3: Row Labels | B3: Sum of Net Sales
A4: Electronics | B4: 3308520
A5: Home Appliances | B5: 1126180
A6: Furniture | B6: 177805
A7: Sports | B7: 168440
A8: Groceries | B8: 63385
A9: Clothing | B9: 41832
A10: Beauty | B10: 20562.9
A11: Office supplies | B11: 9665.2
A12: Grand Total | B12: 4916390.1

Sheet Paymode
A3: Row Labels | B3: Sum of Net Sales
A4: Cash | B4: 184382.5
A5: Credit Card | B5: 1082800
A6: Debit | B6: 1347985.2
A7: Net Banking | B7: 1029608
A8: UPI | B8: 1271614.4
A9: Grand Total | B9: 4916390.1

Sheet Order status
A3: Row Labels | B3: Count of Order ID
A4: Cancelled | B4: 11
A5: Delivered | B5: 10
A6: Processing | B6: 6
A7: Returned | B7: 8
A8: Shipped | B8: 15
A9: Grand Total | B9: 50

Sheet Table
